.gitignore
excel_example.PNG
html_example.PNG
readme.md
setup.cfg
setup.py
test.py
excel_to_html/__init__.py
excel_to_html/color_utilities.py
excel_to_html/main.py
excel_to_html/static_values.py
excel_to_html.egg-info/PKG-INFO
excel_to_html.egg-info/SOURCES.txt
excel_to_html.egg-info/dependency_links.txt
excel_to_html.egg-info/requires.txt
excel_to_html.egg-info/top_level.txt
tests/output1.html
tests/output2.html
tests/output3.html
tests/output4.html
tests/output5.html
tests/output6.html
tests/test.py
tests/test.xlsx
tests/test2.xlsx