Metadata-Version: 1.1
Name: excel-to-html
Version: 1.0.0
Summary: A package that converts excel sheets to HTML tables
Home-page: https://github.com/mwhamilton/excel_to_html
Author: Matthew Hamilton
Author-email: mwhamilton6@gmail.com
License: MIT
Download-URL: https://github.com/mwhamilton/excel_to_html/archive/1.0.0.tar.gz
Platform: UNKNOWN
Classifier: License :: OSI Approved :: MIT License
Classifier: Programming Language :: Python :: 3
Classifier: Programming Language :: Python :: 3.7
